universal_test_runner/__init__.py
universal_test_runner/cli.py
universal_test_runner/commands.py
universal_test_runner/context.py
universal_test_runner/runner.py
universal_test_runner-0.7.0.dist-info/entry_points.txt
universal_test_runner-0.7.0.dist-info/LICENSE
universal_test_runner-0.7.0.dist-info/WHEEL
universal_test_runner-0.7.0.dist-info/METADATA
universal_test_runner-0.7.0.dist-info/RECORD
