Metadata-Version: 2.3
Name: universal-test-runner
Version: 0.7.0
Summary: Universal, language-aware unit test runner.
Keywords: testing,test-runner,pytest
Author-email: David Brownman <beamneocube@gmail.com>
Requires-Python: >=3.9
Classifier: Programming Language :: Python :: 3
Classifier: Development Status :: 3 - Alpha
Classifier: Environment :: Console
Classifier: License :: OSI Approved :: MIT License
Classifier: Operating System :: OS Independent
Classifier: Topic :: Software Development :: Testing
Requires-Dist: click==8.1.3
Requires-Dist: colorama==0.4.6
Requires-Dist: pyright==1.1.376 ; extra == "ci"
Requires-Dist: ruff==0.5.7 ; extra == "ci"
Requires-Dist: twine==5.1.1 ; extra == "release"
Requires-Dist: build==1.2.1 ; extra == "release"
Requires-Dist: pytest==7.3.1 ; extra == "test"
Requires-Dist: responses==0.23.1 ; extra == "test"
Project-URL: Author, https://xavd.id
Project-URL: Bug Tracker, https://github.com/xavdid/universal-test-runner/issues
Project-URL: Changelog, https://github.com/xavdid/universal-test-runner/blob/main/CHANGELOG.md
Project-URL: Homepage, https://github.com/xavdid/universal-test-runner
Provides-Extra: ci
Provides-Extra: release
Provides-Extra: test
